setup.cfg
setup.py
TwitterToReddit/__init__.py
TwitterToReddit/__main__.py
TwitterToReddit/bot.py
TwitterToReddit/constants.py
TwitterToReddit/utils.py
TwitterToReddit.egg-info/PKG-INFO
TwitterToReddit.egg-info/SOURCES.txt
TwitterToReddit.egg-info/dependency_links.txt
TwitterToReddit.egg-info/entry_points.txt
TwitterToReddit.egg-info/requires.txt
TwitterToReddit.egg-info/top_level.txt