Metadata-Version: 1.1
Name: TwitterToReddit
Version: 0.1.4
Summary: Simple python bot that crossposts Tweets to reddit
Home-page: https://github.com/l3d00m/TwitterToReddit/
Author: Thomas Lue
Author-email: thomasvanhalen01@gmail.com
License: MIT
Download-URL: https://github.com/l3d00m/TwitterToReddit/tarball/v0.1.4
Keywords: reddit,twitter,bot
Platform: UNKNOWN
Classifier: Development Status :: 3 - Alpha
Classifier: Topic :: Utilities
Classifier: Programming Language :: Python :: 3.4
